pymskt/__init__.py
pymskt/__init__.pyc
pymskt/cython_functions.cpython-310-darwin.so
pymskt/cython_functions.cpython-38-darwin.so
pymskt/cython/cython_functions.c
pymskt/cython/cython_functions.pyx
pymskt/image/__init__.py
pymskt/image/__init__.pyc
pymskt/image/cartilage_processing.py
pymskt/image/main.py
pymskt/image/main.pyc
pymskt/image/meniscus_processing.py
pymskt/image/t2.py
pymskt/mesh/__init__.py
pymskt/mesh/createMesh.py
pymskt/mesh/io.py
pymskt/mesh/meshCartilage.py
pymskt/mesh/meshRegistration.py
pymskt/mesh/meshTools.py
pymskt/mesh/meshTransform.py
pymskt/mesh/meshes.py
pymskt/mesh/utils.py
pymskt/mesh/anatomical/__init__.py
pymskt/mesh/anatomical/femur_anatomical_coordinate_system.py
pymskt/mesh/anatomical/femur_cylinder.py
pymskt/mesh/anatomical/femur_long_axis.py
pymskt/statistics/__init__.py
pymskt/statistics/main.py
pymskt/statistics/pca.py
pymskt/statistics/ssm.py
pymskt/utils/__init__.py
pymskt/utils/main.py
pymskt/utils/testing.py
mskt-0.1.18.dist-info/METADATA
mskt-0.1.18.dist-info/WHEEL
mskt-0.1.18.dist-info/top_level.txt
mskt-0.1.18.dist-info/RECORD
