Metadata-Version: 2.1
Name: mskt
Version: 0.1.18
Summary: vtk helper tools/functions for musculoskeletal analyses
Author-email: Anthony Gatti <anthony.a.gatti@gmail.com>
License: MIT
Project-URL: Homepage, https://github.com/gattia/pymskt/
Project-URL: Documentation, https://anthonygattiphd.com/pymskt/
Keywords: python
Classifier: Development Status :: 3 - Alpha
Classifier: License :: OSI Approved :: MIT License
Classifier: Topic :: Scientific/Engineering
Classifier: Programming Language :: Python :: 3
Requires-Python: >=3.7
Requires-Dist: point-cloud-utils
Requires-Dist: numpy
Requires-Dist: Cython >=0.29
Requires-Dist: pyacvd
Requires-Dist: pyvista
Requires-Dist: scipy
Requires-Dist: SimpleITK
Requires-Dist: vtk
Requires-Dist: param
Requires-Dist: jupyter
Requires-Dist: notebook
Requires-Dist: traittypes
Requires-Dist: pymeshfix
Requires-Dist: pyfocusr
Requires-Dist: itkwidgets
Requires-Dist: cycpd
